{"settings":"25a83891597493279ddd776abd96b193","version":"4.4.2","files":{"apps_soccer_admin_py":{"hash":"bb59b77355eec18dfeb803c177e90e8b","index":{"relative_filename":"apps/soccer/admin.py","nums":[1,11,0,0,0,0,0],"html_filename":"apps_soccer_admin_py.html"}},"apps_soccer___init___py":{"hash":"182b2dca469bf063cbcf996d517b03da","index":{"relative_filename":"apps/soccer/__init__.py","nums":[1,0,0,0,0,0,0],"html_filename":"apps_soccer___init___py.html"}},"apps_soccer_models_py":{"hash":"d9e5afceb711a0c69a76e1c819726c55","index":{"relative_filename":"apps/soccer/models.py","nums":[1,61,0,10,0,0,0],"html_filename":"apps_soccer_models_py.html"}},"apps_soccer_views_py":{"hash":"41e5443960aae5f69b467fc5fa65b92d","index":{"relative_filename":"apps/soccer/views.py","nums":[1,9,0,0,0,0,0],"html_filename":"apps_soccer_views_py.html"}},"config___init___py":{"hash":"182b2dca469bf063cbcf996d517b03da","index":{"relative_filename":"config/__init__.py","nums":[1,0,0,0,0,0,0],"html_filename":"config___init___py.html"}},"apps___init___py":{"hash":"182b2dca469bf063cbcf996d517b03da","index":{"relative_filename":"apps/__init__.py","nums":[1,0,0,0,0,0,0],"html_filename":"apps___init___py.html"}},"templates___init___py":{"hash":"4911cff48f6b9e153df4c1a3ecaded19","index":{"relative_filename":"templates/__init__.py","nums":[1,0,0,0,0,0,0],"html_filename":"templates___init___py.html"}},"apps_soccer_tests_py":{"hash":"ddc904e4c95b1b7c6355e4e93c69c525","index":{"relative_filename":"apps/soccer/tests.py","nums":[1,1,0,1,0,0,0],"html_filename":"apps_soccer_tests_py.html"}},"__init___py":{"hash":"182b2dca469bf063cbcf996d517b03da","index":{"relative_filename":"__init__.py","nums":[1,0,0,0,0,0,0],"html_filename":"__init___py.html"}}},"format":1}